<?xml version="1.0" encoding="UTF-8"?>

<beans xmlns="http://www.springframework.org/schema/beans"
	xmlns:xsi="http://www.w3.org/2001/XMLSchema-instance"
	xmlns:context="http://www.springframework.org/schema/context"
	xsi:schemaLocation="http://www.springframework.org/schema/beans
 http://www.springframework.org/schema/beans/spring-beans.xsd
 http://www.springframework.org/schema/context
 http://www.springframework.org/schema/context/spring-context.xsd">

	<bean class="byConstructor.Laptop" id="laptop" autowire="constructor">
		<property name="name" value="Dell" />
		<property name="price" value="30000.00" />
		
		
	</bean>

   <bean class="byConstructor.Processor" id="processor" >
       <property name="processorName" value="Intel Core i3"/>
       <property  name="RAM" value="4 GB"/>
       
   </bean>
	

</beans>